LICENSE
MANIFEST.in
README.md
requirements.txt
setup.cfg
setup.py
versioneer.py
botcity/web/__init__.py
botcity/web/_version.py
botcity/web/bot.py
botcity/web/compat.py
botcity/web/config.py
botcity/web/cv2find.py
botcity/web/parsers.py
botcity/web/util.py
botcity/web/browsers/__init__.py
botcity/web/browsers/chrome.py
botcity/web/browsers/edge.py
botcity/web/browsers/firefox.py
botcity/web/browsers/ie.py
botcity/web/browsers/undetected_chrome.py
botcity_framework_web.egg-info/PKG-INFO
botcity_framework_web.egg-info/SOURCES.txt
botcity_framework_web.egg-info/dependency_links.txt
botcity_framework_web.egg-info/requires.txt
botcity_framework_web.egg-info/top_level.txt
tests/test_browser.py
tests/test_keyboard.py
tests/test_mouse.py
tests/test_vision.py