Metadata-Version: 2.4
Name: botcity-framework-web
Version: 1.0.3
Home-page: https://www.github.com/botcity-dev/botcity-framework-web-python
Requires-Python: >=3.7
License-File: LICENSE
Requires-Dist: botcity-framework-base>=0.2.2
Requires-Dist: beautifulsoup4
Requires-Dist: numpy
Requires-Dist: opencv-python
Requires-Dist: pillow
Requires-Dist: selenium<5,>=4.10
Requires-Dist: undetected-chromedriver
Requires-Dist: packaging
Dynamic: description
Dynamic: description-content-type
Dynamic: home-page
Dynamic: license-file
Dynamic: requires-dist
Dynamic: requires-python
